wpdetect/__init__.py
wpdetect/__main__.py
wpdetect/cli_store.py
wpdetect/constants.py
wpdetect/utils/__init__.py
wpdetect/utils/print.py
wpdetect/utils/url.py
wpdetect/utils/wp.py
wpdetect-1.4.10.dist-info/METADATA
wpdetect-1.4.10.dist-info/WHEEL
wpdetect-1.4.10.dist-info/entry_points.txt
wpdetect-1.4.10.dist-info/licenses/LICENSE.txt
wpdetect-1.4.10.dist-info/RECORD
