Metadata-Version: 2.1
Name: wpdetect
Version: 1.4.10
Summary: A WordPress detection tool, detects if a website is running WordPress
Project-URL: Homepage, https://github.com/IamLizu/wpdetect
Project-URL: Bug Tracker, https://github.com/IamLizu/wpdetect/issues
Project-URL: Changelog, https://github.com/IamLizu/wpdetect/blob/master/CHANGELOG.md
Author-email: S M Mahmudul Hasan <he@smmahmudulhasan.com>
License-File: LICENSE.txt
Classifier: Development Status :: 5 - Production/Stable
Classifier: Intended Audience :: Developers
Classifier: License :: OSI Approved :: MIT License
Classifier: Operating System :: OS Independent
Classifier: Programming Language :: Python :: 3
Classifier: Topic :: Software Development :: Build Tools
Requires-Python: >=3.4
Requires-Dist: click
Requires-Dist: pyfiglet
Requires-Dist: requests
